dateint/__init__.py
dateint/config.py
dateint/convert.py
dateint/core.py
dateint/exception.py
dateint-0.1.0.dist-info/LICENSE
dateint-0.1.0.dist-info/METADATA
dateint-0.1.0.dist-info/WHEEL
dateint-0.1.0.dist-info/top_level.txt
dateint-0.1.0.dist-info/RECORD
