Metadata-Version: 2.1
Name: dateint
Version: 0.1.0
Summary: Helper library for manipulation of formatted date/datetime values.
Home-page: https://github.com/amaralbf/dateint
Author: Bruno Amaral
Author-email: amaralbf@gmail.com
Project-URL: Documentation, https://amaralbf.github.io/dateint/
Classifier: Environment :: Console
Classifier: Intended Audience :: Developers
Classifier: License :: OSI Approved :: MIT License
Classifier: Operating System :: OS Independent
Classifier: Programming Language :: Python
Classifier: Programming Language :: Python :: 3
Classifier: Programming Language :: Python :: 3 :: Only
Classifier: Programming Language :: Python :: 3.7
Classifier: Programming Language :: Python :: 3.8
Classifier: Programming Language :: Python :: 3.9
Classifier: Topic :: Software Development :: Libraries
Classifier: Topic :: Software Development :: Libraries :: Python Modules
Requires-Python: >=3.7,<4.0
License-File: LICENSE
Requires-Dist: pandas
Requires-Dist: python-dateutil
